speakit-0.1.4.dist-info/METADATA
speakit-0.1.4.dist-info/WHEEL
speakit/__init__.py
speakit/speakit.cp39-win_amd64.pyd
speakit-0.1.4.dist-info/RECORD
