Metadata-Version: 2.1
Name: speakit
Version: 0.1.4
Classifier: Programming Language :: Python
Author: Mike Roberts <42875462+mrob95@users.noreply.github.com>
Author-email: Mike Roberts <42875462+mrob95@users.noreply.github.com>
